solution_efe_client_notification/__init__.py
solution_efe_client_notification/notificationService.py
solution_efe_client_notification-1.0.0.dist-info/METADATA
solution_efe_client_notification-1.0.0.dist-info/WHEEL
solution_efe_client_notification-1.0.0.dist-info/top_level.txt
solution_efe_client_notification-1.0.0.dist-info/RECORD
